{
	"trade":"Mewcantiwe Convoy",
	"tradeLiner":"Winew Convoy",
	"tradeSmuggler":"Smuggwew",
	"smallTrader":"Twadew",
	
	"patrolSmall":"Fast Picket",
	"patrolMedium":"Patwow",
	"patrolLarge":"Detachment",
	
	"leagueEnforcer":"Enfowcew",
	"leagueArmada":"Gwand Awmada",
	"supplyFleet":"Suppwy Fweet",
	
	"commerceRaiders":"Commewce Waidews",
	"raider":"Waidew",
	
	"sacredProtectors":"Sacwed Pwotectows",
	
	"investigators":"Investigatows",
	
	"inspectionFleet":"Inspection Fweet",
	"taskForce":"Task Fowce",
	
	"scavengerSmall":"Pwospectow",
	"scavengerMedium":"Scavengew",
	"scavengerLarge":"Sawvage Fweet",
	
	"foodReliefFleet":"Wewief Convoy",
	
	"shrinePilgrims":"Wuddic Piwgwims",
	"academyFleet":"Academy Shuttwe Sewvice",
	
	"mercScout":"Mewcenawy Scout",
	"mercBountyHunter":"Bounty Huntew",
	"mercPrivateer":"Pwivateew",
	"mercPatrol":"Mewcenawy Patwow",
	"mercArmada":"Mewcenawy Company",
	
	"battlestation":"Battwestation",
	
	#"":"",
}